{
    "href": "https://api.spotify.com/v1/playlists/4fQbcRcOMfuWZZL05V8y4I/tracks?offset=0&limit=100",
    "items": [
        {
            "added_at": "2023-08-13T16:30:25Z",
            "added_by": {
                "external_urls": {
                    "spotify": "https://open.spotify.com/user/31bfzg4fpcogoh7btjial6dxuqie"
                },
                "href": "https://api.spotify.com/v1/users/31bfzg4fpcogoh7btjial6dxuqie",
                "id": "31bfzg4fpcogoh7btjial6dxuqie",
                "type": "user",
                "uri": "spotify:user:31bfzg4fpcogoh7btjial6dxuqie"
            },
            "is_local": false,
            "primary_color": null,
            "track": {
                "album": {
                    "album_type": "single",
                    "artists": [
                        {
                            "external_urls": {
                                "spotify": "https://open.spotify.com/artist/5BS8KSKJPeLeXfABQx0bXl"
                            },
                            "href": "https://api.spotify.com/v1/artists/5BS8KSKJPeLeXfABQx0bXl",
                            "id": "5BS8KSKJPeLeXfABQx0bXl",
                            "name": "Mina Okabe",
                            "type": "artist",
                            "uri": "spotify:artist:5BS8KSKJPeLeXfABQx0bXl"
                        }
                    ],
                    "external_urls": {
                        "spotify": "https://open.spotify.com/album/4VLxnKcNSnVyxw4ByPzQVs"
                    },
                    "href": "https://api.spotify.com/v1/albums/4VLxnKcNSnVyxw4ByPzQVs",
                    "id": "4VLxnKcNSnVyxw4ByPzQVs",
                    "images": [
                        {
                            "height": 640,
                            "url": "https://i.scdn.co/image/ab67616d0000b273fc03b97c30ce11e30e65e389",
                            "width": 640
                        },
                        {
                            "height": 300,
                            "url": "https://i.scdn.co/image/ab67616d00001e02fc03b97c30ce11e30e65e389",
                            "width": 300
                        },
                        {
                            "height": 64,
                            "url": "https://i.scdn.co/image/ab67616d00004851fc03b97c30ce11e30e65e389",
                            "width": 64
                        }
                    ],
                    "is_playable": true,
                    "name": "Every Second",
                    "release_date": "2021-05-21",
                    "release_date_precision": "day",
                    "total_tracks": 1,
                    "type": "album",
                    "uri": "spotify:album:4VLxnKcNSnVyxw4ByPzQVs"
                },
                "artists": [
                    {
                        "external_urls": {
                            "spotify": "https://open.spotify.com/artist/5BS8KSKJPeLeXfABQx0bXl"
                        },
                        "href": "https://api.spotify.com/v1/artists/5BS8KSKJPeLeXfABQx0bXl",
                        "id": "5BS8KSKJPeLeXfABQx0bXl",
                        "name": "Mina Okabe",
                        "type": "artist",
                        "uri": "spotify:artist:5BS8KSKJPeLeXfABQx0bXl"
                    }
                ],
                "disc_number": 1,
                "duration_ms": 182076,
                "episode": false,
                "explicit": false,
                "external_ids": {
                    "isrc": "DKUM72100269"
                },
                "external_urls": {
                    "spotify": "https://open.spotify.com/track/6dquCx5KAW5jCgGgoTlghL"
                },
                "href": "https://api.spotify.com/v1/tracks/6dquCx5KAW5jCgGgoTlghL",
                "id": "6dquCx5KAW5jCgGgoTlghL",
                "is_local": false,
                "is_playable": true,
                "name": "Every Second",
                "popularity": 63,
                "preview_url": "https://p.scdn.co/mp3-preview/d0d405e0518ba690d30cb1870b4bacb4997c6536?cid=ec7c9f15df104a378127fe610dbeb080",
                "track": true,
                "track_number": 1,
                "type": "track",
                "uri": "spotify:track:6dquCx5KAW5jCgGgoTlghL"
            },
            "video_thumbnail": {
                "url": null
            }
        }
    ],
    "limit": 100,
    "next": null,
    "offset": 0,
    "previous": null,
    "total": 1
}